streamhist/__init__.py
streamhist/histogram.py
streamhist/utils.py
streamhist/version.py
streamhist/weighted_histogram.py
streamhist/test/__init__.py
streamhist/test/profile.py
streamhist/test/test_histogram.py
streamhist-0.1.0.dist-info/METADATA
streamhist-0.1.0.dist-info/WHEEL
streamhist-0.1.0.dist-info/top_level.txt
streamhist-0.1.0.dist-info/zip-safe
streamhist-0.1.0.dist-info/RECORD
